LICENSE
MANIFEST.in
README.rst
setup.py
aws_manager/__init__.py
aws_manager/admin.py
aws_manager/models.py
aws_manager/tests.py
aws_manager/urls.py
aws_manager/views.py
aws_manager/management/__init__.py
aws_manager/management/commands/__init__.py
aws_manager/management/commands/aws-server.py
django_aws_manager.egg-info/PKG-INFO
django_aws_manager.egg-info/SOURCES.txt
django_aws_manager.egg-info/dependency_links.txt
django_aws_manager.egg-info/requires.txt
django_aws_manager.egg-info/top_level.txt