Metadata-Version: 1.1
Name: django-aws-manager
Version: 0.1.2.5
Summary: A Django app to manage Amazon AWS servers.
Home-page: https://github.com/jromich/django-aws-manager
Author: Joe Rothermich
Author-email: author@email.com
License: MIT License
Platform: UNKNOWN
Classifier: Environment :: Web Environment
Classifier: Framework :: Django
Classifier: Intended Audience :: Developers
Classifier: License :: OSI Approved :: MIT License
Classifier: Operating System :: OS Independent
Classifier: Programming Language :: Python
Classifier: Programming Language :: Python :: 2.7
Classifier: Topic :: Internet :: WWW/HTTP
Classifier: Topic :: Internet :: WWW/HTTP :: Dynamic Content
